LICENSE
MANIFEST.in
README.md
__init__.py
pjstealth.py
test.py
js/chrome.app.js
js/chrome.canvasfeature.js
js/chrome.canvasfeature2.js
js/chrome.clientrectfeature.js
js/chrome.csi.js
js/chrome.cssfeature.js
js/chrome.fontsfeature.js
js/chrome.hairline.js
js/chrome.load.times.js
js/chrome.runtime.js
js/chrome.videofeature.js
js/chrome.videofeature2.js
js/chrome.webrtc.js
js/generate.magic.arrays.js
js/hookfuc.headless.js
js/iframe.contentWindow.js
js/media.codecs.js
js/navigator.appVersion.js
js/navigator.deviceMemory.js
js/navigator.hardwareConcurrency.js
js/navigator.language.js
js/navigator.languages.js
js/navigator.permissions.js
js/navigator.platform.js
js/navigator.plugins.js
js/navigator.userAgent.js
js/navigator.userAgentData.js
js/navigator.vendor.js
js/utils.js
js/webgl.vendor.js
js/window.outerdimensions.js
pjstealth/__init__.py
pjstealth/env_data.py
pjstealth/pjstealth.py
pjstealth/stealth.py
pjstealth/feature/chrome.app.js
pjstealth/feature/chrome.canvasfeature.js
pjstealth/feature/chrome.canvasfeature2.js
pjstealth/feature/chrome.clientrectfeature.js
pjstealth/feature/chrome.csi.js
pjstealth/feature/chrome.cssfeature.js
pjstealth/feature/chrome.fontsfeature.js
pjstealth/feature/chrome.hairline.js
pjstealth/feature/chrome.load.times.js
pjstealth/feature/chrome.runtime.js
pjstealth/feature/chrome.screen.colordepth.js
pjstealth/feature/chrome.videofeature.js
pjstealth/feature/chrome.webdriver.js
pjstealth/feature/chrome.webrtc.js
pjstealth/feature/generate.magic.arrays.js
pjstealth/feature/hookfuc.headless.js
pjstealth/feature/iframe.contentWindow.js
pjstealth/feature/media.codecs.js
pjstealth/feature/navigator.appVersion.js
pjstealth/feature/navigator.deviceMemory.js
pjstealth/feature/navigator.hardwareConcurrency.js
pjstealth/feature/navigator.language.js
pjstealth/feature/navigator.languages.js
pjstealth/feature/navigator.permissions.js
pjstealth/feature/navigator.platform.js
pjstealth/feature/navigator.plugins.js
pjstealth.egg-info/PKG-INFO
pjstealth.egg-info/SOURCES.txt
pjstealth.egg-info/dependency_links.txt
pjstealth.egg-info/top_level.txt
pjstealth-0.41.dist-info/LICENSE
pjstealth-0.41.dist-info/METADATA
pjstealth-0.41.dist-info/WHEEL
pjstealth-0.41.dist-info/top_level.txt
pjstealth-0.41.dist-info/RECORD
