Metadata-Version: 2.1
Name: pjstealth
Version: 0.41
Summary: 浏览器特征抹除，及浏览器指纹随机化
Home-page: https://github.com/winner-hue/pjstealth
Author: winner-hue
Author-email: 1344246287@qq.com
License-File: LICENSE
